hand_gest_example/__init__.py
hand_gest_example/handGestTest.py
hand_gest_recog_example_by_pranjal-0.1.0.dist-info/METADATA
hand_gest_recog_example_by_pranjal-0.1.0.dist-info/WHEEL
hand_gest_recog_example_by_pranjal-0.1.0.dist-info/top_level.txt
hand_gest_recog_example_by_pranjal-0.1.0.dist-info/RECORD
