Metadata-Version: 2.1
Name: hand-gest-recog-example-by-pranjal
Version: 0.1.0
Summary: A hand gesture recognition example package.
Home-page: https://github.com/Pranjal-Prabhat/hand-recognizer
Author: Pranjal Prabhat
Classifier: Programming Language :: Python :: 3
Classifier: License :: OSI Approved :: MIT License
Classifier: Operating System :: OS Independent
Requires-Python: >=3.6
Requires-Dist: mediapipe
Requires-Dist: opencv-python
